ann_linkage_clustering/__init__.py
ann_linkage_clustering/helpers.py
ann_linkage_clustering/lib.py
ann_linkage_clustering-0.11.1.dist-info/LICENSE
ann_linkage_clustering-0.11.1.dist-info/METADATA
ann_linkage_clustering-0.11.1.dist-info/WHEEL
ann_linkage_clustering-0.11.1.dist-info/top_level.txt
ann_linkage_clustering-0.11.1.dist-info/RECORD
