Metadata-Version: 2.1
Name: ann-linkage-clustering
Version: 0.11.1
Summary: Linkage clustering via Approximate Nearest Neighbors
Home-page: https://github.com/FredHutch/find-cags
Author: Samuel Minot
Author-email: sminot@fredhutch.org
License: UNKNOWN
Project-URL: Bug Reports, https://github.com/fredhutch/find-cags/issues
Project-URL: Source, https://github.com/fredhutch/find-cags/
Keywords: science clustering
Platform: UNKNOWN
Classifier: Intended Audience :: Science/Research
Classifier: License :: OSI Approved :: MIT License
Classifier: Programming Language :: Python :: 3
Classifier: Programming Language :: Python :: 3.6
Requires-Dist: pandas (>=0.20.3)
Requires-Dist: numpy (>=1.13.1)
Requires-Dist: scipy (>=0.19.1)
Requires-Dist: awscli
Requires-Dist: boto3 (>=1.4.7)
Requires-Dist: python-dateutil (==2.6.0)
Requires-Dist: fastcluster (>=1.1.24)
Requires-Dist: nmslib (>=1.7.2)
Requires-Dist: scikit-learn (>=0.19.2)
